trame/__init__.py
trame/modules/__init__.py
trame/modules/simput.py
trame/widgets/__init__.py
trame/widgets/simput.py
trame_simput/__init__.py
trame_simput/core/__init__.py
trame_simput/core/domains.py
trame_simput/core/factory.py
trame_simput/core/mapping.py
trame_simput/core/proxy.py
trame_simput/core/utils.py
trame_simput/core/ui/__init__.py
trame_simput/core/ui/manager.py
trame_simput/core/ui/utils.py
trame_simput/core/ui/resolvers/__init__.py
trame_simput/core/ui/resolvers/vuetify.py
trame_simput/module/__init__.py
trame_simput/module/core.py
trame_simput/module/protocol.py
trame_simput/module/serve/demo.html
trame_simput/module/serve/vue-trame_simput.common.js
trame_simput/module/serve/vue-trame_simput.common.js.map
trame_simput/module/serve/vue-trame_simput.umd.js
trame_simput/module/serve/vue-trame_simput.umd.js.map
trame_simput/module/serve/vue-trame_simput.umd.min.js
trame_simput/module/serve/vue-trame_simput.umd.min.js.map
trame_simput/module/serve/vue3-trame_simput.umd.js
trame_simput/widgets/__init__.py
trame_simput/widgets/simput.py
trame_simput-2.6.3.dist-info/METADATA
trame_simput-2.6.3.dist-info/WHEEL
trame_simput-2.6.3.dist-info/licenses/LICENSE
trame_simput-2.6.3.dist-info/RECORD
